cli.py
cmdbikes-0.1.11.dist-info/LICENSE
cmdbikes-0.1.11.dist-info/METADATA
cmdbikes-0.1.11.dist-info/WHEEL
cmdbikes-0.1.11.dist-info/entry_points.txt
cmdbikes-0.1.11.dist-info/top_level.txt
cmdbikes-0.1.11.dist-info/RECORD
