Metadata-Version: 2.2
Name: cmdbikes
Version: 0.1.11
Summary: Bike sharing at your terminal
Home-page: https://github.com/eskerda/cmdbikes
Author: Lluís Esquerda
Author-email: eskerda@gmail.com
Keywords: Citybikes bike sharing
Classifier: Development Status :: 4 - Beta
Classifier: Intended Audience :: End Users/Desktop
Classifier: Topic :: Utilities
Classifier: Programming Language :: Python
Classifier: Programming Language :: Python :: 2
Classifier: Programming Language :: Python :: 2.7
Classifier: Programming Language :: Python :: 3
Classifier: Programming Language :: Python :: 3.5
Classifier: Programming Language :: Python :: 3.6
Classifier: Programming Language :: Python :: 3.7
Classifier: Programming Language :: Python :: 3.8
Classifier: License :: OSI Approved :: MIT License
Requires-Python: >=2.7, !=3.0.*, !=3.1.*, !=3.2.*, !=3.3.*, !=3.4.*
License-File: LICENSE
Requires-Dist: python-citybikes>=0.1.3
Requires-Dist: click
Requires-Dist: colorama
Requires-Dist: geopy
Requires-Dist: iso3166
Dynamic: author
Dynamic: author-email
Dynamic: classifier
Dynamic: description
Dynamic: home-page
Dynamic: keywords
Dynamic: requires-dist
Dynamic: requires-python
Dynamic: summary
